RabbitHole/__init__.py
RabbitHole/__version__.py
RabbitHole/rabbithole.py
RabbitHole_SSH-0.1.2.dist-info/METADATA
RabbitHole_SSH-0.1.2.dist-info/RECORD
RabbitHole_SSH-0.1.2.dist-info/WHEEL
RabbitHole_SSH-0.1.2.dist-info/entry_points.txt
RabbitHole_SSH-0.1.2.dist-info/top_level.txt
