Metadata-Version: 2.1
Name: RabbitHole-SSH
Version: 0.1.2
Summary: YAML defined SSH Tunnel, SOCKS5 Proxy and SSHFS Mount
Home-page: https://github.com/dohsimpson/RabbitHole
Author: Doh Simpson
Author-email: mydohsimpson@gmail.com
License: GPLv3
Platform: UNKNOWN
Classifier: License :: OSI Approved :: GNU General Public License v3 (GPLv3)
Classifier: Programming Language :: Python
Classifier: Programming Language :: Python :: 2
Classifier: Programming Language :: Python :: 3
Classifier: Programming Language :: Python :: Implementation :: CPython
Classifier: Programming Language :: Python :: Implementation :: PyPy
Requires-Python: >=2.6
Requires-Dist: pyyaml
